odoo/addons/stock_auto_move/README.rst
odoo/addons/stock_auto_move/__init__.py
odoo/addons/stock_auto_move/__manifest__.py
odoo/addons/stock_auto_move/data/procurement_group.xml
odoo/addons/stock_auto_move/demo/stock_location.xml
odoo/addons/stock_auto_move/demo/stock_location_route.xml
odoo/addons/stock_auto_move/demo/stock_rule.xml
odoo/addons/stock_auto_move/i18n/ca.po
odoo/addons/stock_auto_move/i18n/de.po
odoo/addons/stock_auto_move/i18n/es.po
odoo/addons/stock_auto_move/i18n/es_MX.po
odoo/addons/stock_auto_move/i18n/fi.po
odoo/addons/stock_auto_move/i18n/fr.po
odoo/addons/stock_auto_move/i18n/hr.po
odoo/addons/stock_auto_move/i18n/it.po
odoo/addons/stock_auto_move/i18n/nl_NL.po
odoo/addons/stock_auto_move/i18n/pt.po
odoo/addons/stock_auto_move/i18n/pt_BR.po
odoo/addons/stock_auto_move/i18n/pt_PT.po
odoo/addons/stock_auto_move/i18n/sl.po
odoo/addons/stock_auto_move/i18n/stock_auto_move.pot
odoo/addons/stock_auto_move/i18n/tr.po
odoo/addons/stock_auto_move/i18n/tr_TR.po
odoo/addons/stock_auto_move/i18n/zh_CN.po
odoo/addons/stock_auto_move/models/__init__.py
odoo/addons/stock_auto_move/models/stock_move.py
odoo/addons/stock_auto_move/models/stock_rule.py
odoo/addons/stock_auto_move/readme/CONFIGURE.rst
odoo/addons/stock_auto_move/readme/CONTRIBUTORS.rst
odoo/addons/stock_auto_move/readme/DESCRIPTION.rst
odoo/addons/stock_auto_move/readme/INSTALL.rst
odoo/addons/stock_auto_move/readme/USAGE.rst
odoo/addons/stock_auto_move/static/description/icon.png
odoo/addons/stock_auto_move/static/description/index.html
odoo/addons/stock_auto_move/tests/__init__.py
odoo/addons/stock_auto_move/tests/test_stock_auto_move.py
odoo/addons/stock_auto_move/views/stock_move.xml
odoo/addons/stock_auto_move/views/stock_rule.xml
odoo14_addon_stock_auto_move-14.0.1.0.1.dev8.dist-info/METADATA
odoo14_addon_stock_auto_move-14.0.1.0.1.dev8.dist-info/WHEEL
odoo14_addon_stock_auto_move-14.0.1.0.1.dev8.dist-info/top_level.txt
odoo14_addon_stock_auto_move-14.0.1.0.1.dev8.dist-info/RECORD
